echo_tts/__init__.py
echo_tts/autoencoder.py
echo_tts/cli.py
echo_tts/inference.py
echo_tts/model.py
echo_tts/py.typed
echo_tts/resources/sampler_presets.json
echo_tts-0.1.4.dist-info/licenses/LICENSE
echo_tts-0.1.4.dist-info/METADATA
echo_tts-0.1.4.dist-info/WHEEL
echo_tts-0.1.4.dist-info/entry_points.txt
echo_tts-0.1.4.dist-info/top_level.txt
echo_tts-0.1.4.dist-info/RECORD
