Metadata-Version: 2.4
Name: echo-tts
Version: 0.1.4
Summary: Echo TTS - Text-to-Speech synthesis with voice cloning
Author: Jordan Darefsky, FoxEngine LTD
License: Apache-2.0
Project-URL: Homepage, https://github.com/FoxEngine-ai/echo-tts
Project-URL: Repository, https://github.com/FoxEngine-ai/echo-tts
Keywords: tts,text-to-speech,voice-cloning,audio,speech-synthesis
Classifier: Development Status :: 4 - Beta
Classifier: Intended Audience :: Developers
Classifier: License :: OSI Approved :: Apache Software License
Classifier: Programming Language :: Python :: 3
Classifier: Programming Language :: Python :: 3.10
Classifier: Programming Language :: Python :: 3.11
Classifier: Programming Language :: Python :: 3.12
Classifier: Topic :: Multimedia :: Sound/Audio :: Speech
Requires-Python: >=3.10
License-File: LICENSE
Requires-Dist: torch>=2.0.0
Requires-Dist: torchaudio>=2.0.0
Requires-Dist: torchcodec>=0.8.1
Requires-Dist: huggingface-hub
Requires-Dist: numpy
Requires-Dist: safetensors
Requires-Dist: einops
Requires-Dist: soundfile
Provides-Extra: gradio
Requires-Dist: gradio>=5.0.0; extra == "gradio"
Provides-Extra: dev
Requires-Dist: pytest; extra == "dev"
Requires-Dist: ruff; extra == "dev"
Dynamic: license-file
